codenamegenerator/__init__.py
codenamegenerator/__main__.py
codenamegenerator/dicts/adjectives.csv
codenamegenerator/dicts/artists.csv
codenamegenerator/dicts/birds.csv
codenamegenerator/dicts/currencies.csv
codenamegenerator/dicts/emotions.csv
codenamegenerator/dicts/fruits.csv
codenamegenerator/dicts/greek_alphabet.csv
codenamegenerator/dicts/japanese_emperors.csv
codenamegenerator/dicts/japanese_food.csv
codenamegenerator/dicts/mobi_notable_scientists_and_hackers.csv
codenamegenerator/dicts/olympians_greek.csv
codenamegenerator/dicts/olympians_roman.csv
codenamegenerator/dicts/periodic_elements.csv
codenamegenerator/dicts/phonetic_alphabet.csv
codenamegenerator-3.1.dist-info/LICENSE
codenamegenerator-3.1.dist-info/METADATA
codenamegenerator-3.1.dist-info/WHEEL
codenamegenerator-3.1.dist-info/top_level.txt
codenamegenerator-3.1.dist-info/RECORD
